{
  "project_info": {
    "project_number": "348401475785",
    "project_id": "instagram-tutorial-2bb53",
    "storage_bucket": "instagram-tutorial-2bb53.appspot.com"
  },
  "client": [
    {
      "client_info": {
        "mobilesdk_app_id": "1:348401475785:android:380acf69b24b97bd1b6d18",
        "android_client_info": {
          "package_name": "com.example.instagram_flutter"
        }
      },
      "oauth_client": [],
      "api_key": [
        {
          "current_key": "AIzaSyBbtYtJkJRF_6KewXbU8dA75oyPdUI4iTE"
        }
      ],
      "services": {
        "appinvite_service": {
          "other_platform_oauth_client": []
        }
      }
    }
  ],
  "configuration_version": "1"
}